Metadata-Version: 2.1
Name: pipetex2tex
Version: 0.0.0
Summary: CL tool to convert tex-files that contain \input{|command} with the actual output of these commands.
Home-page: https://github.com/benmaier/pipetex2tex
Author: Benjamin F. Maier
Author-email: contact@benmaier.org
License: MIT
Project-URL: Documentation, http://pipetex2tex.benmaier.org
Project-URL: Contributing Statement, https://github.com/benmaier/pipetex2tex/blob/master/CONTRIBUTING.md
Project-URL: Bug Reports, https://github.com/benmaier/pipetex2tex/issues
Project-URL: Source, https://github.com/benmaier/pipetex2tex/
Project-URL: PyPI, https://pypi.org/project/pipetex2tex/
Classifier: License :: OSI Approved :: MIT License
Classifier: Programming Language :: Python :: 3.6
Classifier: Programming Language :: Python :: 3.7
Classifier: Programming Language :: Python :: 3.8
Classifier: Programming Language :: Python :: 3.9
Classifier: Programming Language :: Python :: 3.10
Classifier: Programming Language :: Python :: 3.11
Requires-Python: >=3.6
License-File: LICENSE
